coaprcs/__init__.py
coaprcs/blockwise.py
coaprcs/credentials.py
coaprcs/defaults.py
coaprcs/error.py
coaprcs/interfaces.py
coaprcs/message.py
coaprcs/messagemanager.py
coaprcs/meta.py
coaprcs/options.py
coaprcs/optiontypes.py
coaprcs/oscore.py
coaprcs/oscore_sitewrapper.py
coaprcs/pipe.py
coaprcs/protocol.py
coaprcs/resource.py
coaprcs/tokenmanager.py
coaprcs/cli/__init__.py
coaprcs/cli/client.py
coaprcs/cli/common.py
coaprcs/cli/defaults.py
coaprcs/cli/fileserver.py
coaprcs/cli/proxy.py
coaprcs/cli/rd.py
coaprcs/numbers/__init__.py
coaprcs/numbers/codes.py
coaprcs/numbers/constants.py
coaprcs/numbers/contentformat.py
coaprcs/numbers/optionnumbers.py
coaprcs/numbers/types.py
coaprcs/proxy/__init__.py
coaprcs/proxy/client.py
coaprcs/proxy/server.py
coaprcs/resourcedirectory/__init__.py
coaprcs/resourcedirectory/client/__init__.py
coaprcs/resourcedirectory/client/register.py
coaprcs/transports/__init__.py
coaprcs/transports/generic_udp.py
coaprcs/transports/oscore.py
coaprcs/transports/rfc8323common.py
coaprcs/transports/simple6.py
coaprcs/transports/simplesocketserver.py
coaprcs/transports/tcp.py
coaprcs/transports/tinydtls.py
coaprcs/transports/tinydtls_server.py
coaprcs/transports/tls.py
coaprcs/transports/udp6.py
coaprcs/transports/ws.py
coaprcs/util/__init__.py
coaprcs/util/cli.py
coaprcs/util/contenttype.py
coaprcs/util/cryptography_additions.py
coaprcs/util/linkformat.py
coaprcs/util/linkformat_pygments.py
coaprcs/util/prettyprint.py
coaprcs/util/pyodide_websockets.py
coaprcs/util/socknumbers.py
coaprcs/util/uri.py
coaprcs/util/asyncio/__init__.py
coaprcs/util/asyncio/getaddrinfo_addrconfig.py
coaprcs/util/asyncio/recvmsg.py
coaprcs/util/asyncio/timeoutdict.py
coaprcs/util/vendored/link_header.py
coaprcs-0.0.8.dist-info/LICENSE
coaprcs-0.0.8.dist-info/METADATA
coaprcs-0.0.8.dist-info/WHEEL
coaprcs-0.0.8.dist-info/top_level.txt
coaprcs-0.0.8.dist-info/RECORD
